icare_nlp/MANIFEST.in
icare_nlp/__init__.py
icare_nlp/object_desc.py
icare_nlp/object_qa.py
icare_nlp/receipt_desc.py
icare_nlp/receipt_qa.py
icare_nlp/task_disp.py
icare_nlp/utils.py
icare_nlp/resources/__init__.py
icare_nlp/resources/category_emb_tensor.pt
icare_nlp/resources/category_tactile_description.json
icare_nlp/resources/desc_words.json
icare_nlp/resources/inv_yolo_obj_class_def.json
icare_nlp/resources/rev_yolo_obj_class_def.json
icare_nlp/resources/yolo_obj_class_def.json
icare_nlp-0.1.dist-info/METADATA
icare_nlp-0.1.dist-info/WHEEL
icare_nlp-0.1.dist-info/top_level.txt
icare_nlp-0.1.dist-info/RECORD
