Metadata-Version: 2.1
Name: icare-nlp
Version: 0.1
Summary: From CV detection to answer questions
Author-email: 23037086r@connect.polyu.hk
Keywords: icare,language
